<?xml version="1.0" encoding="UTF-8" standalone="no"?><Empleados><empleado><id>1</id><apellido>Fernandez</apellido><Dep>10</Dep><salario>1000.45</salario></empleado><empleado><id>2</id><apellido>Gil</apellido><Dep>20</Dep><salario>2420.6</salario></empleado><empleado><id>3</id><apellido>Lopez</apellido><Dep>10</Dep><salario>3000.0</salario></empleado><empleado><id>4</id><apellido>Ramos</apellido><Dep>40</Dep><salario>4000.87</salario></empleado><empleado><id>5</id><apellido>Sevilla</apellido><Dep>30</Dep><salario>2200.0</salario></empleado><empleado><id>6</id><apellido>Castilla</apellido><Dep>30</Dep><salario>1435.87</salario></empleado><empleado><id>7</id><apellido>Rey</apellido><Dep>20</Dep><salario>2000.0</salario></empleado><empleado><id>8</id><apellido>GONZALEZ</apellido><Dep>10</Dep><salario>1230.87</salario></empleado></Empleados>